swcpm/__init__.py
swcpm/main.py
swcpm/info/__init__.py
swcpm/info/info_command.py
swcpm/info/info_func.py
swcpm/install/__init__.py
swcpm/install/install_command.py
swcpm/install/install_func.py
swcpm/remove/__init__.py
swcpm/remove/remove_command.py
swcpm/remove/remove_func.py
swcpm/run/__init__.py
swcpm/run/run_command.py
swcpm/run/run_func.py
swcpm/update/__init__.py
swcpm/update/update_command.py
swcpm/update/update_func.py
swcpm/wget/__init__.py
swcpm/wget/wget_command.py
swcpm/wget/wget_func.py
swcpm-0.1.7.dist-info/LICENSE.txt
swcpm-0.1.7.dist-info/METADATA
swcpm-0.1.7.dist-info/WHEEL
swcpm-0.1.7.dist-info/entry_points.txt
swcpm-0.1.7.dist-info/top_level.txt
swcpm-0.1.7.dist-info/RECORD
